properunits/__init__.py
properunits/base.py
properunits/energy.py
properunits/force.py
properunits/length.py
properunits/mass.py
properunits/pressure.py
properunits/temperature.py
properunits-0.1.0.dist-info/licenses/LICENSE
properunits-0.1.0.dist-info/METADATA
properunits-0.1.0.dist-info/WHEEL
properunits-0.1.0.dist-info/top_level.txt
properunits-0.1.0.dist-info/RECORD
