Metadata-Version: 2.4
Name: properunits
Version: 0.1.0
Summary: A simple framework to work with physical magnitudes
Author-email: Angel Yanguas-Gil <angel.yanguas@gmail.com>
Project-URL: Homepage, https://github.com/anglyan/properunits.git
Project-URL: Bug Tracker, https://github.com/anglyan/properunits/issues
Project-URL: Documentation, https://properunits.readthedocs.io/en/latest/
Keywords: physics,conversion,units,SI
Classifier: Programming Language :: Python :: 3
Classifier: Operating System :: OS Independent
License-File: LICENSE
Provides-Extra: dev
Requires-Dist: pytest; extra == "dev"
Provides-Extra: test
Requires-Dist: pytest; extra == "test"
Dynamic: license-file
